Workbook

Sheet Overview
A1: WebEngage Custom Agents — Clarification Overview
A2: A stakeholder decision workbook for the proposed Java / Spring Boot custom-agent platform
A4: Total questions | C4: Blocking decisions | E4: Decided | G4: Completion
A5: =COUNTIF(Questions!$A$6:$A$77,"<>") -> 72 | C5: =COUNTIF(Questions!$H$6:$H$77,"Yes") -> 38 | E5: =COUNTIF(Questions!$L$6:$L$77,"Decided") -> 72 | G5: =IFERROR(E5/A5,0) -> 1
A8: Working agreement: resolve all blocking questions, record one accountable owner, and mark a row Decided only after stakeholder approval. Recommended defaults are implementation assumptions—not silent decisions.
A10: Decision progress by theme
A11: Theme | B11: Total | C11: Critical | D11: Blocking | E11: Decided | F11: Open | G11: Progress
A12: Custom-agent programming model | B12: =COUNTIF(Questions!$B$6:$B$77,A12) -> 6 | C12: =COUNTIFS(Questions!$B$6:$B$77,A12,Questions!$G$6:$G$77,"Critical") -> 3 | D12: =COUNTIFS(Questions!$B$6:$B$77,A12,Questions!$H$6:$H$77,"Yes") -> 3 | E12: =COUNTIFS(Questions!$B$6:$B$77,A12,Questions!$L$6:$L$77,"Decided") -> 6 | F12: =B12-E12 -> 0 | G12: =IFERROR(E12/B12,0) -> 1
A13: Core Agentic Layer | B13: =COUNTIF(Questions!$B$6:$B$77,A13) -> 7 | C13: =COUNTIFS(Questions!$B$6:$B$77,A13,Questions!$G$6:$G$77,"Critical") -> 4 | D13: =COUNTIFS(Questions!$B$6:$B$77,A13,Questions!$H$6:$H$77,"Yes") -> 4 | E13: =COUNTIFS(Questions!$B$6:$B$77,A13,Questions!$L$6:$L$77,"Decided") -> 7 | F13: =B13-E13 -> 0 | G13: =IFERROR(E13/B13,0) -> 1
A14: WebEngage tools | B14: =COUNTIF(Questions!$B$6:$B$77,A14) -> 7 | C14: =COUNTIFS(Questions!$B$6:$B$77,A14,Questions!$G$6:$G$77,"Critical") -> 3 | D14: =COUNTIFS(Questions!$B$6:$B$77,A14,Questions!$H$6:$H$77,"Yes") -> 3 | E14: =COUNTIFS(Questions!$B$6:$B$77,A14,Questions!$L$6:$L$77,"Decided") -> 7 | F14: =B14-E14 -> 0 | G14: =IFERROR(E14/B14,0) -> 1
A15: Agent and execution APIs | B15: =COUNTIF(Questions!$B$6:$B$77,A15) -> 6 | C15: =COUNTIFS(Questions!$B$6:$B$77,A15,Questions!$G$6:$G$77,"Critical") -> 2 | D15: =COUNTIFS(Questions!$B$6:$B$77,A15,Questions!$H$6:$H$77,"Yes") -> 2 | E15: =COUNTIFS(Questions!$B$6:$B$77,A15,Questions!$L$6:$L$77,"Decided") -> 6 | F15: =B15-E15 -> 0 | G15: =IFERROR(E15/B15,0) -> 1
A16: Scheduling | B16: =COUNTIF(Questions!$B$6:$B$77,A16) -> 6 | C16: =COUNTIFS(Questions!$B$6:$B$77,A16,Questions!$G$6:$G$77,"Critical") -> 5 | D16: =COUNTIFS(Questions!$B$6:$B$77,A16,Questions!$H$6:$H$77,"Yes") -> 5 | E16: =COUNTIFS(Questions!$B$6:$B$77,A16,Questions!$L$6:$L$77,"Decided") -> 6 | F16: =B16-E16 -> 0 | G16: =IFERROR(E16/B16,0) -> 1
A17: Authentication and authorization | B17: =COUNTIF(Questions!$B$6:$B$77,A17) -> 8 | C17: =COUNTIFS(Questions!$B$6:$B$77,A17,Questions!$G$6:$G$77,"Critical") -> 7 | D17: =COUNTIFS(Questions!$B$6:$B$77,A17,Questions!$H$6:$H$77,"Yes") -> 7 | E17: =COUNTIFS(Questions!$B$6:$B$77,A17,Questions!$L$6:$L$77,"Decided") -> 8 | F17: =B17-E17 -> 0 | G17: =IFERROR(E17/B17,0) -> 1
A18: Conversation and audit logging | B18: =COUNTIF(Questions!$B$6:$B$77,A18) -> 8 | C18: =COUNTIFS(Questions!$B$6:$B$77,A18,Questions!$G$6:$G$77,"Critical") -> 5 | D18: =COUNTIFS(Questions!$B$6:$B$77,A18,Questions!$H$6:$H$77,"Yes") -> 5 | E18: =COUNTIFS(Questions!$B$6:$B$77,A18,Questions!$L$6:$L$77,"Decided") -> 8 | F18: =B18-E18 -> 0 | G18: =IFERROR(E18/B18,0) -> 1
A19: Persistence and infrastructure | B19: =COUNTIF(Questions!$B$6:$B$77,A19) -> 6 | C19: =COUNTIFS(Questions!$B$6:$B$77,A19,Questions!$G$6:$G$77,"Critical") -> 5 | D19: =COUNTIFS(Questions!$B$6:$B$77,A19,Questions!$H$6:$H$77,"Yes") -> 5 | E19: =COUNTIFS(Questions!$B$6:$B$77,A19,Questions!$L$6:$L$77,"Decided") -> 6 | F19: =B19-E19 -> 0 | G19: =IFERROR(E19/B19,0) -> 1
A20: Technology choices | B20: =COUNTIF(Questions!$B$6:$B$77,A20) -> 5 | C20: =COUNTIFS(Questions!$B$6:$B$77,A20,Questions!$G$6:$G$77,"Critical") -> 1 | D20: =COUNTIFS(Questions!$B$6:$B$77,A20,Questions!$H$6:$H$77,"Yes") -> 1 | E20: =COUNTIFS(Questions!$B$6:$B$77,A20,Questions!$L$6:$L$77,"Decided") -> 5 | F20: =B20-E20 -> 0 | G20: =IFERROR(E20/B20,0) -> 1
A21: Reliability and operations | B21: =COUNTIF(Questions!$B$6:$B$77,A21) -> 7 | C21: =COUNTIFS(Questions!$B$6:$B$77,A21,Questions!$G$6:$G$77,"Critical") -> 2 | D21: =COUNTIFS(Questions!$B$6:$B$77,A21,Questions!$H$6:$H$77,"Yes") -> 2 | E21: =COUNTIFS(Questions!$B$6:$B$77,A21,Questions!$L$6:$L$77,"Decided") -> 7 | F21: =B21-E21 -> 0 | G21: =IFERROR(E21/B21,0) -> 1
A22: Delivery scope | B22: =COUNTIF(Questions!$B$6:$B$77,A22) -> 6 | C22: =COUNTIFS(Questions!$B$6:$B$77,A22,Questions!$G$6:$G$77,"Critical") -> 1 | D22: =COUNTIFS(Questions!$B$6:$B$77,A22,Questions!$H$6:$H$77,"Yes") -> 1 | E22: =COUNTIFS(Questions!$B$6:$B$77,A22,Questions!$L$6:$L$77,"Decided") -> 6 | F22: =B22-E22 -> 0 | G22: =IFERROR(E22/B22,0) -> 1
A24: How to use this workbook
A25: 1. Filter the Questions tab by Primary stakeholder and Blocking?. 2. Enter a concrete response, decision owner, and due date. 3. Use In Review while validating and Blocked only when a named dependency exists. 4. Change Status to Decided after approval. 5. Review this Overview tab until all Blocking decisions are resolved.

Sheet Questions
A1: WebEngage Custom Agents — Stakeholder Clarification Tracker
A2: Complete all Critical / Blocking questions before implementation. Yellow columns are stakeholder-owned inputs.
A3: Generated 31 Jul 2026 • 72 questions • Update one accountable decision owner per row
A5: ID | B5: Theme | C5: Clarifying question | D5: Decision / recommended default | E5: Primary stakeholder | F5: Supporting stakeholders | G5: Priority | H5: Blocking? | I5: Why it matters | J5: Response / decision | K5: Decision owner | L5: Status | M5: Due date | N5: Notes / follow-up
A6: Q01 | B6: Custom-agent programming model | C6: When users ‘write their own agents,’ what artifact will they provide? | D6: Choose one: declarative definition; Java source upload; compiled JAR/plugin; or Java classes deployed with this service. Recommended: declarative definitions with trusted Java tool components. | E6: Product | F6: Platform Architecture; Security / IAM; Backend Engineering | G6: Critical | H6: Yes | I6: The choice determines deployment, isolation, security, and lifecycle architecture. | J6: Declarative definitions like role play, instruction/Rules, output format, other context inputs like extternal file etc. Trusted tools selected from the pre defined webengage tools. | K6: Product Team | L6: Decided
A7: Q02 | B7: Custom-agent programming model | C7: Must new or updated agents become available without rebuilding or restarting the service? | D7: Recommended: yes for declarative definitions; controlled deployment for trusted Java extensions. | E7: Product | F7: Platform Architecture; SRE / Infrastructure | G7: High | H7: No | I7: Clarifies whether runtime registration and hot reload are required. | J7: Yes, as all the agent related information is stored in DB, the code should use that info to spawn an agent | K7: Engineering | L7: Decided
A8: Q03 | B8: Custom-agent programming model | C8: Do agents require draft, published, and versioned states, or should every update become active immediately? | D8: Recommended: Draft → Published → Retired with immutable published versions. | E8: Product | F8: Backend Engineering; Data Privacy / Compliance | G8: High | H8: No | I8: Defines safe authoring, rollback, and audit behavior. | J8: Yes, Draft → Published → Retired with immutable published versions. | L8: Decided
A9: Q04 | B9: Custom-agent programming model | C9: Can an agent invoke any registered tool, or only an explicit per-agent allowlist? | D9: Recommended: explicit allowlist, validated at publish and run time. | E9: Security / IAM | F9: Product; Core Platform / Tool Owners | G9: Critical | H9: Yes | I9: Controls privilege boundaries and limits unintended actions. | J9: Allowed list for now | L9: Decided
A10: Q05 | B10: Custom-agent programming model | C10: Should each agent define an input and output JSON Schema? | D10: Recommended: yes; require input schema and allow optional output schema. | E10: Product | F10: Platform Architecture; Backend Engineering | G10: High | H10: No | I10: Enables validation, discoverability, and stable API contracts. | J10: The input schema should be prepared using the information provided at the time of agent creation. The user should be able to define their own input sections. Also provision to provide few examples too at the time of agent creation. Output schema can be asked at the time of agent creation. Will iterate on the output | L10: Decided
A11: Q06 | B11: Custom-agent programming model | C11: Can agents store configuration or secrets, and how should secrets be represented? | D11: Recommended: store non-secret configuration; reference secrets by vault identifier only. | E11: Security / IAM | F11: SRE / Infrastructure; Backend Engineering | G11: Critical | H11: Yes | I11: Prevents credentials from leaking into definitions and transcripts. | J11: No, Can refer to the Vault secrets. | L11: Decided
A12: Q07 | B12: Core Agentic Layer | C12: What is the Core Agentic Layer endpoint, HTTP method, and request/response contract? | D12: Provide OpenAPI or representative request/response examples, including errors. | E12: Core Agentic Layer | F12: Platform Architecture; Backend Engineering | G12: Critical | H12: Yes | I12: The orchestration client cannot be implemented without a stable contract. | J12: Not yet defined but open for suggestions, The Input/output can follow the OpenAI contract. | L12: Decided
A13: Q08 | B13: Core Agentic Layer | C13: Is the tool-calling protocol OpenAI-compatible or WebEngage-specific? | D13: Recommended: document a versioned internal contract even if it mirrors OpenAI tool calling. | E13: Core Agentic Layer | F13: Platform Architecture | G13: Critical | H13: Yes | I13: Determines message types, tool-call parsing, and compatibility strategy. | J13: webengage specific MCPs | L13: Decided
A14: Q09 | B14: Core Agentic Layer | C14: Should this service perform the full agent loop: send context, receive tool calls, execute tools, return results, and repeat until a final answer? | D14: Recommended: yes; the custom-agent service owns tool execution and the Core Agentic Layer owns model generation. | E14: Platform Architecture | F14: Core Agentic Layer; Core Platform / Tool Owners | G14: Critical | H14: Yes | I14: Establishes the service boundary and orchestration responsibility. | J14: yes; the custom-agent service owns tool execution and the Core Agentic Layer owns model generation. | L14: Decided
A15: Q10 | B15: Core Agentic Layer | C15: What maximum iterations, wall-clock timeout, token limit, and cost limit should apply per execution? | D15: Recommended starting point: 10 iterations, 5-minute timeout, configurable token/cost ceilings. | E15: Product | F15: Core Agentic Layer; SRE / Infrastructure | G15: Critical | H15: Yes | I15: Prevents runaway loops and unbounded latency or spend. | J15: starting point: 10 iterations, 5-minute timeout, configurable token/cost ceilings. Should be configurable as needed | L15: Decided
A16: Q11 | B16: Core Agentic Layer | C16: Should multiple tool calls returned in one model response execute in parallel? | D16: Recommended: parallel only for tools declared read-only and concurrency-safe. | E16: Platform Architecture | F16: Core Platform / Tool Owners; Backend Engineering | G16: High | H16: No | I16: Affects performance, ordering, and side-effect safety. | J16: parallel only for tools declared read-only and concurrency-safe. | L16: Decided
A17: Q12 | B17: Core Agentic Layer | C17: Should conversation context persist across separate executions or only within one run? | D17: Recommended: isolate by run initially; add explicit conversation/session IDs if cross-run continuity is needed. | E17: Product | F17: Data Privacy / Compliance; Platform Architecture | G17: High | H17: No | I17: Determines storage model, privacy scope, and context assembly. | J17: isolate by run initially; add explicit conversation/session IDs if cross-run continuity is needed. | L17: Decided
A18: Q13 | B18: Core Agentic Layer | C18: Is a mock Core Agentic Layer acceptable for local development and automated tests? | D18: Recommended: yes, with deterministic scripted tool-call scenarios. | E18: QA / Release Engineering | F18: Core Agentic Layer; Backend Engineering | G18: Medium | H18: No | I18: Enables reliable development and integration testing without model dependency. | J18: yes, with deterministic scripted tool-call scenarios. | L18: Decided
A19: Q14 | B19: WebEngage tools | C19: What are the initial tools and their request/response contracts? | D19: Provide tool names, descriptions, JSON schemas, owners, side-effect classification, and examples. | E19: Core Platform / Tool Owners | F19: Product; Platform Architecture | G19: Critical | H19: Yes | I19: Tool definitions are foundational inputs to agent configuration and execution. | J19: Open, will add a doc for the same. suggest em a doc format to declare the tolls | L19: Decided
... A77: Q72 | B77: Delivery scope | C77: Should backward-compatible API/database evolution and optimistic locking be included in the first version? | D77: Recommended: versioned migrations and optimistic locking from the outset; API compatibility rules documented. | E77: Platform Architecture | F77: Backend Engineering; Product | G77: High | H77: No | I77: Reduces lost updates and unsafe future evolution. | J77: Skip to start with | L77: Decided

Sheet Stakeholder Routing
A1: Stakeholder Routing & Review Responsibilities
A2: Use this tab to distribute the Questions tab to the right decision-makers and track their review load.
A4: Stakeholder | B4: Primary focus | C4: Input expected | D4: Primary questions | E4: Blocking questions | F4: Suggested accountable role
A5: Product | B5: Product scope, behavior, sharing model, and acceptance criteria | C5: Choose business defaults and approve the first-release boundary | D5: =COUNTIF(Questions!$E$6:$E$77,A5) -> 22 | E5: =COUNTIFS(Questions!$E$6:$E$77,A5,Questions!$H$6:$H$77,"Yes") -> 12 | F5: Product Manager / Agent Platform Owner
A6: Platform Architecture | B6: Service boundaries, runtime model, contracts, and extensibility | C6: Approve architecture decisions and internal platform alignment | D6: =COUNTIF(Questions!$E$6:$E$77,A6) -> 12 | E6: =COUNTIFS(Questions!$E$6:$E$77,A6,Questions!$H$6:$H$77,"Yes") -> 5 | F6: Principal / Staff Architect
A7: Core Agentic Layer | B7: LLM-generation API, tool-calling protocol, limits, and errors | C7: Supply a versioned contract, examples, and test endpoint or mock | D7: =COUNTIF(Questions!$E$6:$E$77,A7) -> 2 | E7: =COUNTIFS(Questions!$E$6:$E$77,A7,Questions!$H$6:$H$77,"Yes") -> 2 | F7: Core Agentic Layer Tech Lead
A8: Core Platform / Tool Owners | B8: Tool schemas, side effects, reliability, and downstream APIs | C8: Document and approve every initial tool contract | D8: =COUNTIF(Questions!$E$6:$E$77,A8) -> 4 | E8: =COUNTIFS(Questions!$E$6:$E$77,A8,Questions!$H$6:$H$77,"Yes") -> 2 | F8: Owning Platform Tech Lead(s)
A9: Security / IAM | B9: Identity, authorization, secrets, delegated access, and approvals | C9: Approve trust boundaries, claims, roles, and sensitive-action controls | D9: =COUNTIF(Questions!$E$6:$E$77,A9) -> 11 | E9: =COUNTIFS(Questions!$E$6:$E$77,A9,Questions!$H$6:$H$77,"Yes") -> 8 | F9: Security Architect / IAM Owner
A10: Data Privacy / Compliance | B10: Retention, PII, audit, encryption, residency, and deletion | C10: Define policy constraints and approve transcript/audit handling | D10: =COUNTIF(Questions!$E$6:$E$77,A10) -> 6 | E10: =COUNTIFS(Questions!$E$6:$E$77,A10,Questions!$H$6:$H$77,"Yes") -> 4 | F10: Privacy / Compliance Owner
A11: SRE / Infrastructure | B11: Deployment, persistence, scheduling, scaling, and observability | C11: Confirm supported infrastructure, SLOs, and operational standards | D11: =COUNTIF(Questions!$E$6:$E$77,A11) -> 8 | E11: =COUNTIFS(Questions!$E$6:$E$77,A11,Questions!$H$6:$H$77,"Yes") -> 5 | F11: SRE / Infrastructure Lead
A12: Backend Engineering | B12: Java/Spring implementation standards and API conventions | C12: Confirm engineering standards and feasibility of proposed defaults | D12: =COUNTIF(Questions!$E$6:$E$77,A12) -> 4 | E12: =COUNTIFS(Questions!$E$6:$E$77,A12,Questions!$H$6:$H$77,"Yes") -> 0 | F12: Backend Engineering Lead
A13: QA / Release Engineering | B13: Test strategy, CI, release gates, and local testability | C13: Approve test strategy and delivery pipeline requirements | D13: =COUNTIF(Questions!$E$6:$E$77,A13) -> 3 | E13: =COUNTIFS(Questions!$E$6:$E$77,A13,Questions!$H$6:$H$77,"Yes") -> 0 | F13: QA / Release Lead
A15: Suggested review sequence
A16: 1. Product + Architecture resolve the programming model, service boundary, and release scope. 2. Core Agentic Layer + Tool Owners provide executable contracts. 3. Security + Privacy approve identity, tool permissions, transcripts, and retention. 4. SRE confirms persistence, scheduling, deployment, capacity, and observability. 5. Engineering + QA finalize implementation conventions and delivery gates.

Sheet Reference
A1: Reference & Response Guidance
A2: Use these definitions to keep stakeholder responses consistent and decision-ready.
A4: Status | B4: Definition | D4: Priority | E4: Definition | G4: Blocking? | H4: Definition | J4: Stakeholder | K4: Primary review focus
A5: Not Started | B5: No stakeholder input has been recorded. | D5: Critical | E5: Required before architecture or implementation can safely proceed. | G5: Yes | H5: Implementation should not begin without a decision. | J5: Product | K5: Product scope, behavior, sharing model, and acceptance criteria
A6: In Review | B6: Input is being discussed or requires validation. | D6: High | E6: Materially affects the first release design or scope. | G6: No | H6: A recommended default can be used temporarily. | J6: Platform Architecture | K6: Service boundaries, runtime model, contracts, and extensibility
A7: Blocked | B7: A dependency prevents a decision. | D7: Medium | E7: Can use a documented default if stakeholders do not override it. | J7: Core Agentic Layer | K7: LLM-generation API, tool-calling protocol, limits, and errors
A8: Decided | B8: A decision is approved and ready for implementation. | J8: Core Platform / Tool Owners | K8: Tool schemas, side effects, reliability, and downstream APIs
J9: Security / IAM | K9: Identity, authorization, secrets, delegated access, and approvals
A10: Response standard | J10: Data Privacy / Compliance | K10: Retention, PII, audit, encryption, residency, and deletion
A11: For every decision, record the chosen option or concrete requirement in ‘Response / decision’, name a single accountable decision owner, update Status to Decided only after approval, and use Notes / follow-up for dependencies or action items. If the recommended default is accepted, state ‘Accept recommended default’ explicitly. | J11: SRE / Infrastructure | K11: Deployment, persistence, scheduling, scaling, and observability
J12: Backend Engineering | K12: Java/Spring implementation standards and API conventions
J13: QA / Release Engineering | K13: Test strategy, CI, release gates, and local testability
